{"nodes": [{"id": "c_users_user_source_repos_axiom_malx_ai_advancedfeaturestate_cs", "label": "AdvancedFeatureState.cs", "file_type": "code", "source_file": "Malx_AI/AdvancedFeatureState.cs", "source_location": "L1"}, {"id": "csharp_namespace:3f9b725fc86a38a4", "label": "Malx_AI", "file_type": "code", "source_file": "Malx_AI/AdvancedFeatureState.cs", "source_location": "L7", "type": "namespace", "metadata": {"kind": "csharp_namespace", "namespace": "Malx_AI"}}, {"id": "c_users_user_source_repos_axiom_malx_ai_advancedfeaturestate_malx_ai_counciltaskhistoryentry", "label": "CouncilTaskHistoryEntry", "file_type": "code", "source_file": "Malx_AI/AdvancedFeatureState.cs", "source_location": "L9", "metadata": {"namespace": "Malx_AI", "scope_chain": ["s115"]}, "_callable": true}, {"id": "guid", "label": "Guid", "file_type": "code", "source_file": "", "source_location": "", "origin_file": "C:\\Users\\user\\source\\repos\\Axiom\\Malx_AI\\AdvancedFeatureState.cs"}, {"id": "datetime", "label": "DateTime", "file_type": "code", "source_file": "", "source_location": "", "origin_file": "C:\\Users\\user\\source\\repos\\Axiom\\Malx_AI\\AdvancedFeatureState.cs"}, {"id": "c_users_user_source_repos_axiom_malx_ai_advancedfeaturestate_malx_ai_counciltaskhistoryentry_tostring", "label": ".ToString()", "file_type": "code", "source_file": "Malx_AI/AdvancedFeatureState.cs", "source_location": "L26", "metadata": {"namespace": "Malx_AI", "scope_chain": ["s115"]}, "_callable": true}, {"id": "c_users_user_source_repos_axiom_malx_ai_advancedfeaturestate_malx_ai_modelperformancelogentry", "label": "ModelPerformanceLogEntry", "file_type": "code", "source_file": "Malx_AI/AdvancedFeatureState.cs", "source_location": "L33", "metadata": {"namespace": "Malx_AI", "scope_chain": ["s115"]}, "_callable": true}, {"id": "c_users_user_source_repos_axiom_malx_ai_advancedfeaturestate_malx_ai_modelperformancelogentry_tostring", "label": ".ToString()", "file_type": "code", "source_file": "Malx_AI/AdvancedFeatureState.cs", "source_location": "L50", "metadata": {"namespace": "Malx_AI", "scope_chain": ["s115"]}, "_callable": true}, {"id": "c_users_user_source_repos_axiom_malx_ai_advancedfeaturestate_malx_ai_workspacetemplateentry", "label": "WorkspaceTemplateEntry", "file_type": "code", "source_file": "Malx_AI/AdvancedFeatureState.cs", "source_location": "L53", "metadata": {"namespace": "Malx_AI", "scope_chain": ["s115"]}, "_callable": true}, {"id": "c_users_user_source_repos_axiom_malx_ai_advancedfeaturestate_malx_ai_workspacetemplateentry_tostring", "label": ".ToString()", "file_type": "code", "source_file": "Malx_AI/AdvancedFeatureState.cs", "source_location": "L66", "metadata": {"namespace": "Malx_AI", "scope_chain": ["s115"]}, "_callable": true}, {"id": "c_users_user_source_repos_axiom_malx_ai_advancedfeaturestate_malx_ai_pinnedmessageentry", "label": "PinnedMessageEntry", "file_type": "code", "source_file": "Malx_AI/AdvancedFeatureState.cs", "source_location": "L69", "metadata": {"namespace": "Malx_AI", "scope_chain": ["s115"]}, "_callable": true}, {"id": "c_users_user_source_repos_axiom_malx_ai_advancedfeaturestate_malx_ai_prompttemplateentry", "label": "PromptTemplateEntry", "file_type": "code", "source_file": "Malx_AI/AdvancedFeatureState.cs", "source_location": "L77", "metadata": {"namespace": "Malx_AI", "scope_chain": ["s115"]}, "_callable": true}, {"id": "c_users_user_source_repos_axiom_malx_ai_advancedfeaturestate_malx_ai_systempromptpresetentry", "label": "SystemPromptPresetEntry", "file_type": "code", "source_file": "Malx_AI/AdvancedFeatureState.cs", "source_location": "L84", "metadata": {"namespace": "Malx_AI", "scope_chain": ["s115"]}, "_callable": true}, {"id": "c_users_user_source_repos_axiom_malx_ai_advancedfeaturestate_malx_ai_workspaceadvancedstatesnapshot", "label": "WorkspaceAdvancedStateSnapshot", "file_type": "code", "source_file": "Malx_AI/AdvancedFeatureState.cs", "source_location": "L91", "metadata": {"namespace": "Malx_AI", "scope_chain": ["s115"]}, "_callable": true}, {"id": "list", "label": "List", "file_type": "code", "source_file": "", "source_location": "", "origin_file": "C:\\Users\\user\\source\\repos\\Axiom\\Malx_AI\\AdvancedFeatureState.cs"}, {"id": "c_users_user_source_repos_axiom_malx_ai_advancedfeaturestate_malx_ai_chatbranch", "label": "ChatBranch", "file_type": "code", "source_file": "Malx_AI/AdvancedFeatureState.cs", "source_location": "L99", "metadata": {"namespace": "Malx_AI", "scope_chain": ["s115"]}, "_callable": true}, {"id": "chatmessagestate", "label": "ChatMessageState", "file_type": "code", "source_file": "", "source_location": "", "origin_file": "C:\\Users\\user\\source\\repos\\Axiom\\Malx_AI\\AdvancedFeatureState.cs"}, {"id": "c_users_user_source_repos_axiom_malx_ai_advancedfeaturestate_malx_ai_chatbranch_tostring", "label": ".ToString()", "file_type": "code", "source_file": "Malx_AI/AdvancedFeatureState.cs", "source_location": "L106", "metadata": {"namespace": "Malx_AI", "scope_chain": ["s115"]}, "_callable": true}, {"id": "c_users_user_source_repos_axiom_malx_ai_advancedfeaturestate_malx_ai_chatadvancedstatesnapshot", "label": "ChatAdvancedStateSnapshot", "file_type": "code", "source_file": "Malx_AI/AdvancedFeatureState.cs", "source_location": "L109", "metadata": {"namespace": "Malx_AI", "scope_chain": ["s115"]}, "_callable": true}, {"id": "workplacechatstateentry", "label": "WorkplaceChatStateEntry", "file_type": "code", "source_file": "", "source_location": "", "origin_file": "C:\\Users\\user\\source\\repos\\Axiom\\Malx_AI\\AdvancedFeatureState.cs"}, {"id": "c_users_user_source_repos_axiom_malx_ai_advancedfeaturestate_malx_ai_workplacechatstateentry", "label": "WorkplaceChatStateEntry", "file_type": "code", "source_file": "Malx_AI/AdvancedFeatureState.cs", "source_location": "L122", "metadata": {"namespace": "Malx_AI", "scope_chain": ["s115"]}, "_callable": true}, {"id": "workplacesessionsnapshot", "label": "WorkplaceSessionSnapshot", "file_type": "code", "source_file": "", "source_location": "", "origin_file": "C:\\Users\\user\\source\\repos\\Axiom\\Malx_AI\\AdvancedFeatureState.cs"}, {"id": "c_users_user_source_repos_axiom_malx_ai_advancedfeaturestate_malx_ai_workspaceadvancedstatepersistence", "label": "WorkspaceAdvancedStatePersistence", "file_type": "code", "source_file": "Malx_AI/AdvancedFeatureState.cs", "source_location": "L129", "metadata": {"namespace": "Malx_AI", "scope_chain": ["s115"]}, "_callable": true}, {"id": "string", "label": "string", "file_type": "code", "source_file": "", "source_location": "", "origin_file": "C:\\Users\\user\\source\\repos\\Axiom\\Malx_AI\\AdvancedFeatureState.cs"}, {"id": "jsonserializeroptions", "label": "JsonSerializerOptions", "file_type": "code", "source_file": "", "source_location": "", "origin_file": "C:\\Users\\user\\source\\repos\\Axiom\\Malx_AI\\AdvancedFeatureState.cs"}, {"id": "c_users_user_source_repos_axiom_malx_ai_advancedfeaturestate_malx_ai_workspaceadvancedstatepersistence_save", "label": ".Save()", "file_type": "code", "source_file": "Malx_AI/AdvancedFeatureState.cs", "source_location": "L136", "metadata": {"namespace": "Malx_AI", "scope_chain": ["s115"]}, "_callable": true}, {"id": "c_users_user_source_repos_axiom_malx_ai_advancedfeaturestate_malx_ai_workspaceadvancedstatepersistence_load", "label": ".Load()", "file_type": "code", "source_file": "Malx_AI/AdvancedFeatureState.cs", "source_location": "L142", "metadata": {"namespace": "Malx_AI", "scope_chain": ["s115"]}, "_callable": true}, {"id": "c_users_user_source_repos_axiom_malx_ai_advancedfeaturestate_malx_ai_chatadvancedstatepersistence", "label": "ChatAdvancedStatePersistence", "file_type": "code", "source_file": "Malx_AI/AdvancedFeatureState.cs", "source_location": "L151", "metadata": {"namespace": "Malx_AI", "scope_chain": ["s115"]}, "_callable": true}, {"id": "c_users_user_source_repos_axiom_malx_ai_advancedfeaturestate_malx_ai_chatadvancedstatepersistence_save", "label": ".Save()", "file_type": "code", "source_file": "Malx_AI/AdvancedFeatureState.cs", "source_location": "L158", "metadata": {"namespace": "Malx_AI", "scope_chain": ["s115"]}, "_callable": true}, {"id": "c_users_user_source_repos_axiom_malx_ai_advancedfeaturestate_malx_ai_chatadvancedstatepersistence_load", "label": ".Load()", "file_type": "code", "source_file": "Malx_AI/AdvancedFeatureState.cs", "source_location": "L164", "metadata": {"namespace": "Malx_AI", "scope_chain": ["s115"]}, "_callable": true}, {"id": "c_users_user_source_repos_axiom_malx_ai_advancedfeaturestate_malx_ai_chatadvancedstatepersistence_getdefaultprompttemplates", "label": ".GetDefaultPromptTemplates()", "file_type": "code", "source_file": "Malx_AI/AdvancedFeatureState.cs", "source_location": "L172", "metadata": {"namespace": "Malx_AI", "scope_chain": ["s115"]}, "_callable": true}, {"id": "c_users_user_source_repos_axiom_malx_ai_advancedfeaturestate_malx_ai_chatadvancedstatepersistence_getbuiltinsystempromptpresets", "label": ".GetBuiltInSystemPromptPresets()", "file_type": "code", "source_file": "Malx_AI/AdvancedFeatureState.cs", "source_location": "L191", "metadata": {"namespace": "Malx_AI", "scope_chain": ["s115"]}, "_callable": true}, {"id": "c_users_user_source_repos_axiom_malx_ai_advancedfeaturestate_malx_ai_chatadvancedstatepersistence_getmostfrequentmodelcombo", "label": ".GetMostFrequentModelCombo()", "file_type": "code", "source_file": "Malx_AI/AdvancedFeatureState.cs", "source_location": "L219", "metadata": {"namespace": "Malx_AI", "scope_chain": ["s115"]}, "_callable": true}, {"id": "ienumerable", "label": "IEnumerable", "file_type": "code", "source_file": "", "source_location": "", "origin_file": "C:\\Users\\user\\source\\repos\\Axiom\\Malx_AI\\AdvancedFeatureState.cs"}], "edges": [{"source": "c_users_user_source_repos_axiom_malx_ai_advancedfeaturestate_cs", "target": "system", "relation": "imports", "context": "import", "confidence": "EXTRACTED", "source_file": "Malx_AI/AdvancedFeatureState.cs", "source_location": "L1", "weight": 1.0, "metadata": {"using_kind": "namespace", "target_fqn": "System", "scope_kind": "file"}}, {"source": "c_users_user_source_repos_axiom_malx_ai_advancedfeaturestate_cs", "target": "system_collections_generic", "relation": "imports", "context": "import", "confidence": "EXTRACTED", "source_file": "Malx_AI/AdvancedFeatureState.cs", "source_location": "L2", "weight": 1.0, "metadata": {"using_kind": "namespace", "target_fqn": "System.Collections.Generic", "scope_kind": "file"}}, {"source": "c_users_user_source_repos_axiom_malx_ai_advancedfeaturestate_cs", "target": "system_io", "relation": "imports", "context": "import", "confidence": "EXTRACTED", "source_file": "Malx_AI/AdvancedFeatureState.cs", "source_location": "L3", "weight": 1.0, "metadata": {"using_kind": "namespace", "target_fqn": "System.IO", "scope_kind": "file"}}, {"source": "c_users_user_source_repos_axiom_malx_ai_advancedfeaturestate_cs", "target": "system_linq", "relation": "imports", "context": "import", "confidence": "EXTRACTED", "source_file": "Malx_AI/AdvancedFeatureState.cs", "source_location": "L4", "weight": 1.0, "metadata": {"using_kind": "namespace", "target_fqn": "System.Linq", "scope_kind": "file"}}, {"source": "c_users_user_source_repos_axiom_malx_ai_advancedfeaturestate_cs", "target": "system_text_json", "relation": "imports", "context": "import", "confidence": "EXTRACTED", "source_file": "Malx_AI/AdvancedFeatureState.cs", "source_location": "L5", "weight": 1.0, "metadata": {"using_kind": "namespace", "target_fqn": "System.Text.Json", "scope_kind": "file"}}, {"source": "c_users_user_source_repos_axiom_malx_ai_advancedfeaturestate_cs", "target": "csharp_namespace:3f9b725fc86a38a4", "relation": "contains", "confidence": "EXTRACTED", "source_file": "Malx_AI/AdvancedFeatureState.cs", "source_location": "L7", "weight": 1.0}, {"source": "c_users_user_source_repos_axiom_malx_ai_advancedfeaturestate_cs", "target": "c_users_user_source_repos_axiom_malx_ai_advancedfeaturestate_malx_ai_counciltaskhistoryentry", "relation": "contains", "confidence": "EXTRACTED", "source_file": "Malx_AI/AdvancedFeatureState.cs", "source_location": "L9", "weight": 1.0}, {"source": "c_users_user_source_repos_axiom_malx_ai_advancedfeaturestate_malx_ai_counciltaskhistoryentry", "target": "guid", "relation": "references", "confidence": "EXTRACTED", "source_file": "Malx_AI/AdvancedFeatureState.cs", "source_location": "L11", "weight": 1.0, "context": "field", "metadata": {"ref_token": "Guid"}}, {"source": "c_users_user_source_repos_axiom_malx_ai_advancedfeaturestate_malx_ai_counciltaskhistoryentry", "target": "guid", "relation": "references", "confidence": "EXTRACTED", "source_file": "Malx_AI/AdvancedFeatureState.cs", "source_location": "L12", "weight": 1.0, "context": "field", "metadata": {"ref_token": "Guid"}}, {"source": "c_users_user_source_repos_axiom_malx_ai_advancedfeaturestate_malx_ai_counciltaskhistoryentry", "target": "datetime", "relation": "references", "confidence": "EXTRACTED", "source_file": "Malx_AI/AdvancedFeatureState.cs", "source_location": "L21", "weight": 1.0, "context": "field", "metadata": {"ref_token": "DateTime"}}, {"source": "c_users_user_source_repos_axiom_malx_ai_advancedfeaturestate_malx_ai_counciltaskhistoryentry", "target": "c_users_user_source_repos_axiom_malx_ai_advancedfeaturestate_malx_ai_counciltaskhistoryentry_tostring", "relation": "method", "confidence": "EXTRACTED", "source_file": "Malx_AI/AdvancedFeatureState.cs", "source_location": "L26", "weight": 1.0}, {"source": "c_users_user_source_repos_axiom_malx_ai_advancedfeaturestate_cs", "target": "c_users_user_source_repos_axiom_malx_ai_advancedfeaturestate_malx_ai_modelperformancelogentry", "relation": "contains", "confidence": "EXTRACTED", "source_file": "Malx_AI/AdvancedFeatureState.cs", "source_location": "L33", "weight": 1.0}, {"source": "c_users_user_source_repos_axiom_malx_ai_advancedfeaturestate_malx_ai_modelperformancelogentry", "target": "datetime", "relation": "references", "confidence": "EXTRACTED", "source_file": "Malx_AI/AdvancedFeatureState.cs", "source_location": "L35", "weight": 1.0, "context": "field", "metadata": {"ref_token": "DateTime"}}, {"source": "c_users_user_source_repos_axiom_malx_ai_advancedfeaturestate_malx_ai_modelperformancelogentry", "target": "c_users_user_source_repos_axiom_malx_ai_advancedfeaturestate_malx_ai_modelperformancelogentry_tostring", "relation": "method", "confidence": "EXTRACTED", "source_file": "Malx_AI/AdvancedFeatureState.cs", "source_location": "L50", "weight": 1.0}, {"source": "c_users_user_source_repos_axiom_malx_ai_advancedfeaturestate_cs", "target": "c_users_user_source_repos_axiom_malx_ai_advancedfeaturestate_malx_ai_workspacetemplateentry", "relation": "contains", "confidence": "EXTRACTED", "source_file": "Malx_AI/AdvancedFeatureState.cs", "source_location": "L53", "weight": 1.0}, {"source": "c_users_user_source_repos_axiom_malx_ai_advancedfeaturestate_malx_ai_workspacetemplateentry", "target": "c_users_user_source_repos_axiom_malx_ai_advancedfeaturestate_malx_ai_workspacetemplateentry_tostring", "relation": "method", "confidence": "EXTRACTED", "source_file": "Malx_AI/AdvancedFeatureState.cs", "source_location": "L66", "weight": 1.0}, {"source": "c_users_user_source_repos_axiom_malx_ai_advancedfeaturestate_cs", "target": "c_users_user_source_repos_axiom_malx_ai_advancedfeaturestate_malx_ai_pinnedmessageentry", "relation": "contains", "confidence": "EXTRACTED", "source_file": "Malx_AI/AdvancedFeatureState.cs", "source_location": "L69", "weight": 1.0}, {"source": "c_users_user_source_repos_axiom_malx_ai_advancedfeaturestate_malx_ai_pinnedmessageentry", "target": "guid", "relation": "references", "confidence": "EXTRACTED", "source_file": "Malx_AI/AdvancedFeatureState.cs", "source_location": "L71", "weight": 1.0, "context": "field", "metadata": {"ref_token": "Guid"}}, {"source": "c_users_user_source_repos_axiom_malx_ai_advancedfeaturestate_malx_ai_pinnedmessageentry", "target": "datetime", "relation": "references", "confidence": "EXTRACTED", "source_file": "Malx_AI/AdvancedFeatureState.cs", "source_location": "L74", "weight": 1.0, "context": "field", "metadata": {"ref_token": "DateTime"}}, {"source": "c_users_user_source_repos_axiom_malx_ai_advancedfeaturestate_cs", "target": "c_users_user_source_repos_axiom_malx_ai_advancedfeaturestate_malx_ai_prompttemplateentry", "relation": "contains", "confidence": "EXTRACTED", "source_file": "Malx_AI/AdvancedFeatureState.cs", "source_location": "L77", "weight": 1.0}, {"source": "c_users_user_source_repos_axiom_malx_ai_advancedfeaturestate_cs", "target": "c_users_user_source_repos_axiom_malx_ai_advancedfeaturestate_malx_ai_systempromptpresetentry", "relation": "contains", "confidence": "EXTRACTED", "source_file": "Malx_AI/AdvancedFeatureState.cs", "source_location": "L84", "weight": 1.0}, {"source": "c_users_user_source_repos_axiom_malx_ai_advancedfeaturestate_cs", "target": "c_users_user_source_repos_axiom_malx_ai_advancedfeaturestate_malx_ai_workspaceadvancedstatesnapshot", "relation": "contains", "confidence": "EXTRACTED", "source_file": "Malx_AI/AdvancedFeatureState.cs", "source_location": "L91", "weight": 1.0}, {"source": "c_users_user_source_repos_axiom_malx_ai_advancedfeaturestate_malx_ai_workspaceadvancedstatesnapshot", "target": "list", "relation": "references", "confidence": "EXTRACTED", "source_file": "Malx_AI/AdvancedFeatureState.cs", "source_location": "L93", "weight": 1.0, "context": "field", "metadata": {"ref_token": "List"}}, {"source": "c_users_user_source_repos_axiom_malx_ai_advancedfeaturestate_malx_ai_workspaceadvancedstatesnapshot", "target": "c_users_user_source_repos_axiom_malx_ai_advancedfeaturestate_malx_ai_counciltaskhistoryentry", "relation": "references", "confidence": "EXTRACTED", "source_file": "Malx_AI/AdvancedFeatureState.cs", "source_location": "L93", "weight": 1.0, "context": "generic_arg", "metadata": {"ref_token": "CouncilTaskHistoryEntry"}}, {"source": "c_users_user_source_repos_axiom_malx_ai_advancedfeaturestate_malx_ai_workspaceadvancedstatesnapshot", "target": "list", "relation": "references", "confidence": "EXTRACTED", "source_file": "Malx_AI/AdvancedFeatureState.cs", "source_location": "L94", "weight": 1.0, "context": "field", "metadata": {"ref_token": "List"}}, {"source": "c_users_user_source_repos_axiom_malx_ai_advancedfeaturestate_malx_ai_workspaceadvancedstatesnapshot", "target": "c_users_user_source_repos_axiom_malx_ai_advancedfeaturestate_malx_ai_workspacetemplateentry", "relation": "references", "confidence": "EXTRACTED", "source_file": "Malx_AI/AdvancedFeatureState.cs", "source_location": "L94", "weight": 1.0, "context": "generic_arg", "metadata": {"ref_token": "WorkspaceTemplateEntry"}}, {"source": "c_users_user_source_repos_axiom_malx_ai_advancedfeaturestate_malx_ai_workspaceadvancedstatesnapshot", "target": "list", "relation": "references", "confidence": "EXTRACTED", "source_file": "Malx_AI/AdvancedFeatureState.cs", "source_location": "L96", "weight": 1.0, "context": "field", "metadata": {"ref_token": "List"}}, {"source": "c_users_user_source_repos_axiom_malx_ai_advancedfeaturestate_malx_ai_workspaceadvancedstatesnapshot", "target": "c_users_user_source_repos_axiom_malx_ai_advancedfeaturestate_malx_ai_modelperformancelogentry", "relation": "references", "confidence": "EXTRACTED", "source_file": "Malx_AI/AdvancedFeatureState.cs", "source_location": "L96", "weight": 1.0, "context": "generic_arg", "metadata": {"ref_token": "ModelPerformanceLogEntry"}}, {"source": "c_users_user_source_repos_axiom_malx_ai_advancedfeaturestate_cs", "target": "c_users_user_source_repos_axiom_malx_ai_advancedfeaturestate_malx_ai_chatbranch", "relation": "contains", "confidence": "EXTRACTED", "source_file": "Malx_AI/AdvancedFeatureState.cs", "source_location": "L99", "weight": 1.0}, {"source": "c_users_user_source_repos_axiom_malx_ai_advancedfeaturestate_malx_ai_chatbranch", "target": "guid", "relation": "references", "confidence": "EXTRACTED", "source_file": "Malx_AI/AdvancedFeatureState.cs", "source_location": "L101", "weight": 1.0, "context": "field", "metadata": {"ref_token": "Guid"}}, {"source": "c_users_user_source_repos_axiom_malx_ai_advancedfeaturestate_malx_ai_chatbranch", "target": "list", "relation": "references", "confidence": "EXTRACTED", "source_file": "Malx_AI/AdvancedFeatureState.cs", "source_location": "L104", "weight": 1.0, "context": "field", "metadata": {"ref_token": "List"}}, {"source": "c_users_user_source_repos_axiom_malx_ai_advancedfeaturestate_malx_ai_chatbranch", "target": "chatmessagestate", "relation": "references", "confidence": "EXTRACTED", "source_file": "Malx_AI/AdvancedFeatureState.cs", "source_location": "L104", "weight": 1.0, "context": "generic_arg", "metadata": {"ref_token": "ChatMessageState"}}, {"source": "c_users_user_source_repos_axiom_malx_ai_advancedfeaturestate_malx_ai_chatbranch", "target": "c_users_user_source_repos_axiom_malx_ai_advancedfeaturestate_malx_ai_chatbranch_tostring", "relation": "method", "confidence": "EXTRACTED", "source_file": "Malx_AI/AdvancedFeatureState.cs", "source_location": "L106", "weight": 1.0}, {"source": "c_users_user_source_repos_axiom_malx_ai_advancedfeaturestate_cs", "target": "c_users_user_source_repos_axiom_malx_ai_advancedfeaturestate_malx_ai_chatadvancedstatesnapshot", "relation": "contains", "confidence": "EXTRACTED", "source_file": "Malx_AI/AdvancedFeatureState.cs", "source_location": "L109", "weight": 1.0}, {"source": "c_users_user_source_repos_axiom_malx_ai_advancedfeaturestate_malx_ai_chatadvancedstatesnapshot", "target": "list", "relation": "references", "confidence": "EXTRACTED", "source_file": "Malx_AI/AdvancedFeatureState.cs", "source_location": "L111", "weight": 1.0, "context": "field", "metadata": {"ref_token": "List"}}, {"source": "c_users_user_source_repos_axiom_malx_ai_advancedfeaturestate_malx_ai_chatadvancedstatesnapshot", "target": "c_users_user_source_repos_axiom_malx_ai_advancedfeaturestate_malx_ai_chatbranch", "relation": "references", "confidence": "EXTRACTED", "source_file": "Malx_AI/AdvancedFeatureState.cs", "source_location": "L111", "weight": 1.0, "context": "generic_arg", "metadata": {"ref_token": "ChatBranch"}}, {"source": "c_users_user_source_repos_axiom_malx_ai_advancedfeaturestate_malx_ai_chatadvancedstatesnapshot", "target": "guid", "relation": "references", "confidence": "EXTRACTED", "source_file": "Malx_AI/AdvancedFeatureState.cs", "source_location": "L112", "weight": 1.0, "context": "field", "metadata": {"ref_token": "Guid"}}, {"source": "c_users_user_source_repos_axiom_malx_ai_advancedfeaturestate_malx_ai_chatadvancedstatesnapshot", "target": "list", "relation": "references", "confidence": "EXTRACTED", "source_file": "Malx_AI/AdvancedFeatureState.cs", "source_location": "L113", "weight": 1.0, "context": "field", "metadata": {"ref_token": "List"}}, {"source": "c_users_user_source_repos_axiom_malx_ai_advancedfeaturestate_malx_ai_chatadvancedstatesnapshot", "target": "c_users_user_source_repos_axiom_malx_ai_advancedfeaturestate_malx_ai_pinnedmessageentry", "relation": "references", "confidence": "EXTRACTED", "source_file": "Malx_AI/AdvancedFeatureState.cs", "source_location": "L113", "weight": 1.0, "context": "generic_arg", "metadata": {"ref_token": "PinnedMessageEntry"}}, {"source": "c_users_user_source_repos_axiom_malx_ai_advancedfeaturestate_malx_ai_chatadvancedstatesnapshot", "target": "list", "relation": "references", "confidence": "EXTRACTED", "source_file": "Malx_AI/AdvancedFeatureState.cs", "source_location": "L114", "weight": 1.0, "context": "field", "metadata": {"ref_token": "List"}}, {"source": "c_users_user_source_repos_axiom_malx_ai_advancedfeaturestate_malx_ai_chatadvancedstatesnapshot", "target": "c_users_user_source_repos_axiom_malx_ai_advancedfeaturestate_malx_ai_prompttemplateentry", "relation": "references", "confidence": "EXTRACTED", "source_file": "Malx_AI/AdvancedFeatureState.cs", "source_location": "L114", "weight": 1.0, "context": "generic_arg", "metadata": {"ref_token": "PromptTemplateEntry"}}, {"source": "c_users_user_source_repos_axiom_malx_ai_advancedfeaturestate_malx_ai_chatadvancedstatesnapshot", "target": "list", "relation": "references", "confidence": "EXTRACTED", "source_file": "Malx_AI/AdvancedFeatureState.cs", "source_location": "L115", "weight": 1.0, "context": "field", "metadata": {"ref_token": "List"}}, {"source": "c_users_user_source_repos_axiom_malx_ai_advancedfeaturestate_malx_ai_chatadvancedstatesnapshot", "target": "c_users_user_source_repos_axiom_malx_ai_advancedfeaturestate_malx_ai_systempromptpresetentry", "relation": "references", "confidence": "EXTRACTED", "source_file": "Malx_AI/AdvancedFeatureState.cs", "source_location": "L115", "weight": 1.0, "context": "generic_arg", "metadata": {"ref_token": "SystemPromptPresetEntry"}}, {"source": "c_users_user_source_repos_axiom_malx_ai_advancedfeaturestate_malx_ai_chatadvancedstatesnapshot", "target": "list", "relation": "references", "confidence": "EXTRACTED", "source_file": "Malx_AI/AdvancedFeatureState.cs", "source_location": "L117", "weight": 1.0, "context": "field", "metadata": {"ref_token": "List"}}, {"source": "c_users_user_source_repos_axiom_malx_ai_advancedfeaturestate_malx_ai_chatadvancedstatesnapshot", "target": "workplacechatstateentry", "relation": "references", "confidence": "EXTRACTED", "source_file": "Malx_AI/AdvancedFeatureState.cs", "source_location": "L117", "weight": 1.0, "context": "generic_arg", "metadata": {"ref_token": "WorkplaceChatStateEntry"}}, {"source": "c_users_user_source_repos_axiom_malx_ai_advancedfeaturestate_cs", "target": "c_users_user_source_repos_axiom_malx_ai_advancedfeaturestate_malx_ai_workplacechatstateentry", "relation": "contains", "confidence": "EXTRACTED", "source_file": "Malx_AI/AdvancedFeatureState.cs", "source_location": "L122", "weight": 1.0}, {"source": "c_users_user_source_repos_axiom_malx_ai_advancedfeaturestate_malx_ai_workplacechatstateentry", "target": "workplacesessionsnapshot", "relation": "references", "confidence": "EXTRACTED", "source_file": "Malx_AI/AdvancedFeatureState.cs", "source_location": "L126", "weight": 1.0, "context": "field", "metadata": {"ref_token": "WorkplaceSessionSnapshot"}}, {"source": "c_users_user_source_repos_axiom_malx_ai_advancedfeaturestate_cs", "target": "c_users_user_source_repos_axiom_malx_ai_advancedfeaturestate_malx_ai_workspaceadvancedstatepersistence", "relation": "contains", "confidence": "EXTRACTED", "source_file": "Malx_AI/AdvancedFeatureState.cs", "source_location": "L129", "weight": 1.0}, {"source": "c_users_user_source_repos_axiom_malx_ai_advancedfeaturestate_malx_ai_workspaceadvancedstatepersistence", "target": "string", "relation": "references", "confidence": "EXTRACTED", "source_file": "Malx_AI/AdvancedFeatureState.cs", "source_location": "L131", "weight": 1.0, "context": "field", "metadata": {"ref_token": "string"}}, {"source": "c_users_user_source_repos_axiom_malx_ai_advancedfeaturestate_malx_ai_workspaceadvancedstatepersistence", "target": "jsonserializeroptions", "relation": "references", "confidence": "EXTRACTED", "source_file": "Malx_AI/AdvancedFeatureState.cs", "source_location": "L132", "weight": 1.0, "context": "field", "metadata": {"ref_token": "JsonSerializerOptions"}}, {"source": "c_users_user_source_repos_axiom_malx_ai_advancedfeaturestate_malx_ai_workspaceadvancedstatepersistence", "target": "c_users_user_source_repos_axiom_malx_ai_advancedfeaturestate_malx_ai_workspaceadvancedstatepersistence_save", "relation": "method", "confidence": "EXTRACTED", "source_file": "Malx_AI/AdvancedFeatureState.cs", "source_location": "L136", "weight": 1.0}, {"source": "c_users_user_source_repos_axiom_malx_ai_advancedfeaturestate_malx_ai_workspaceadvancedstatepersistence_save", "target": "c_users_user_source_repos_axiom_malx_ai_advancedfeaturestate_malx_ai_workspaceadvancedstatesnapshot", "relation": "references", "confidence": "EXTRACTED", "source_file": "Malx_AI/AdvancedFeatureState.cs", "source_location": "L136", "weight": 1.0, "context": "parameter_type", "metadata": {"ref_token": "WorkspaceAdvancedStateSnapshot"}}, {"source": "c_users_user_source_repos_axiom_malx_ai_advancedfeaturestate_malx_ai_workspaceadvancedstatepersistence", "target": "c_users_user_source_repos_axiom_malx_ai_advancedfeaturestate_malx_ai_workspaceadvancedstatepersistence_load", "relation": "method", "confidence": "EXTRACTED", "source_file": "Malx_AI/AdvancedFeatureState.cs", "source_location": "L142", "weight": 1.0}, {"source": "c_users_user_source_repos_axiom_malx_ai_advancedfeaturestate_malx_ai_workspaceadvancedstatepersistence_load", "target": "c_users_user_source_repos_axiom_malx_ai_advancedfeaturestate_malx_ai_workspaceadvancedstatesnapshot", "relation": "references", "confidence": "EXTRACTED", "source_file": "Malx_AI/AdvancedFeatureState.cs", "source_location": "L142", "weight": 1.0, "context": "return_type", "metadata": {"ref_token": "WorkspaceAdvancedStateSnapshot"}}, {"source": "c_users_user_source_repos_axiom_malx_ai_advancedfeaturestate_cs", "target": "c_users_user_source_repos_axiom_malx_ai_advancedfeaturestate_malx_ai_chatadvancedstatepersistence", "relation": "contains", "confidence": "EXTRACTED", "source_file": "Malx_AI/AdvancedFeatureState.cs", "source_location": "L151", "weight": 1.0}, {"source": "c_users_user_source_repos_axiom_malx_ai_advancedfeaturestate_malx_ai_chatadvancedstatepersistence", "target": "string", "relation": "references", "confidence": "EXTRACTED", "source_file": "Malx_AI/AdvancedFeatureState.cs", "source_location": "L153", "weight": 1.0, "context": "field", "metadata": {"ref_token": "string"}}, {"source": "c_users_user_source_repos_axiom_malx_ai_advancedfeaturestate_malx_ai_chatadvancedstatepersistence", "target": "jsonserializeroptions", "relation": "references", "confidence": "EXTRACTED", "source_file": "Malx_AI/AdvancedFeatureState.cs", "source_location": "L154", "weight": 1.0, "context": "field", "metadata": {"ref_token": "JsonSerializerOptions"}}, {"source": "c_users_user_source_repos_axiom_malx_ai_advancedfeaturestate_malx_ai_chatadvancedstatepersistence", "target": "c_users_user_source_repos_axiom_malx_ai_advancedfeaturestate_malx_ai_chatadvancedstatepersistence_save", "relation": "method", "confidence": "EXTRACTED", "source_file": "Malx_AI/AdvancedFeatureState.cs", "source_location": "L158", "weight": 1.0}, {"source": "c_users_user_source_repos_axiom_malx_ai_advancedfeaturestate_malx_ai_chatadvancedstatepersistence_save", "target": "c_users_user_source_repos_axiom_malx_ai_advancedfeaturestate_malx_ai_chatadvancedstatesnapshot", "relation": "references", "confidence": "EXTRACTED", "source_file": "Malx_AI/AdvancedFeatureState.cs", "source_location": "L158", "weight": 1.0, "context": "parameter_type", "metadata": {"ref_token": "ChatAdvancedStateSnapshot"}}, {"source": "c_users_user_source_repos_axiom_malx_ai_advancedfeaturestate_malx_ai_chatadvancedstatepersistence", "target": "c_users_user_source_repos_axiom_malx_ai_advancedfeaturestate_malx_ai_chatadvancedstatepersistence_load", "relation": "method", "confidence": "EXTRACTED", "source_file": "Malx_AI/AdvancedFeatureState.cs", "source_location": "L164", "weight": 1.0}, {"source": "c_users_user_source_repos_axiom_malx_ai_advancedfeaturestate_malx_ai_chatadvancedstatepersistence_load", "target": "c_users_user_source_repos_axiom_malx_ai_advancedfeaturestate_malx_ai_chatadvancedstatesnapshot", "relation": "references", "confidence": "EXTRACTED", "source_file": "Malx_AI/AdvancedFeatureState.cs", "source_location": "L164", "weight": 1.0, "context": "return_type", "metadata": {"ref_token": "ChatAdvancedStateSnapshot"}}, {"source": "c_users_user_source_repos_axiom_malx_ai_advancedfeaturestate_malx_ai_chatadvancedstatepersistence", "target": "c_users_user_source_repos_axiom_malx_ai_advancedfeaturestate_malx_ai_chatadvancedstatepersistence_getdefaultprompttemplates", "relation": "method", "confidence": "EXTRACTED", "source_file": "Malx_AI/AdvancedFeatureState.cs", "source_location": "L172", "weight": 1.0}, {"source": "c_users_user_source_repos_axiom_malx_ai_advancedfeaturestate_malx_ai_chatadvancedstatepersistence_getdefaultprompttemplates", "target": "list", "relation": "references", "confidence": "EXTRACTED", "source_file": "Malx_AI/AdvancedFeatureState.cs", "source_location": "L172", "weight": 1.0, "context": "return_type", "metadata": {"ref_token": "List"}}, {"source": "c_users_user_source_repos_axiom_malx_ai_advancedfeaturestate_malx_ai_chatadvancedstatepersistence_getdefaultprompttemplates", "target": "c_users_user_source_repos_axiom_malx_ai_advancedfeaturestate_malx_ai_prompttemplateentry", "relation": "references", "confidence": "EXTRACTED", "source_file": "Malx_AI/AdvancedFeatureState.cs", "source_location": "L172", "weight": 1.0, "context": "generic_arg", "metadata": {"ref_token": "PromptTemplateEntry"}}, {"source": "c_users_user_source_repos_axiom_malx_ai_advancedfeaturestate_malx_ai_chatadvancedstatepersistence", "target": "c_users_user_source_repos_axiom_malx_ai_advancedfeaturestate_malx_ai_chatadvancedstatepersistence_getbuiltinsystempromptpresets", "relation": "method", "confidence": "EXTRACTED", "source_file": "Malx_AI/AdvancedFeatureState.cs", "source_location": "L191", "weight": 1.0}, {"source": "c_users_user_source_repos_axiom_malx_ai_advancedfeaturestate_malx_ai_chatadvancedstatepersistence_getbuiltinsystempromptpresets", "target": "list", "relation": "references", "confidence": "EXTRACTED", "source_file": "Malx_AI/AdvancedFeatureState.cs", "source_location": "L191", "weight": 1.0, "context": "return_type", "metadata": {"ref_token": "List"}}, {"source": "c_users_user_source_repos_axiom_malx_ai_advancedfeaturestate_malx_ai_chatadvancedstatepersistence_getbuiltinsystempromptpresets", "target": "c_users_user_source_repos_axiom_malx_ai_advancedfeaturestate_malx_ai_systempromptpresetentry", "relation": "references", "confidence": "EXTRACTED", "source_file": "Malx_AI/AdvancedFeatureState.cs", "source_location": "L191", "weight": 1.0, "context": "generic_arg", "metadata": {"ref_token": "SystemPromptPresetEntry"}}, {"source": "c_users_user_source_repos_axiom_malx_ai_advancedfeaturestate_malx_ai_chatadvancedstatepersistence", "target": "c_users_user_source_repos_axiom_malx_ai_advancedfeaturestate_malx_ai_chatadvancedstatepersistence_getmostfrequentmodelcombo", "relation": "method", "confidence": "EXTRACTED", "source_file": "Malx_AI/AdvancedFeatureState.cs", "source_location": "L219", "weight": 1.0}, {"source": "c_users_user_source_repos_axiom_malx_ai_advancedfeaturestate_malx_ai_chatadvancedstatepersistence_getmostfrequentmodelcombo", "target": "ienumerable", "relation": "references", "confidence": "EXTRACTED", "source_file": "Malx_AI/AdvancedFeatureState.cs", "source_location": "L219", "weight": 1.0, "context": "parameter_type", "metadata": {"ref_token": "IEnumerable"}}, {"source": "c_users_user_source_repos_axiom_malx_ai_advancedfeaturestate_malx_ai_chatadvancedstatepersistence_getmostfrequentmodelcombo", "target": "c_users_user_source_repos_axiom_malx_ai_advancedfeaturestate_malx_ai_modelperformancelogentry", "relation": "references", "confidence": "EXTRACTED", "source_file": "Malx_AI/AdvancedFeatureState.cs", "source_location": "L219", "weight": 1.0, "context": "generic_arg", "metadata": {"ref_token": "ModelPerformanceLogEntry"}}], "raw_calls": [{"caller_nid": "c_users_user_source_repos_axiom_malx_ai_advancedfeaturestate_malx_ai_counciltaskhistoryentry_tostring", "callee": "IsNullOrWhiteSpace", "is_member_call": true, "source_file": "C:\\Users\\user\\source\\repos\\Axiom\\Malx_AI\\AdvancedFeatureState.cs", "source_location": "L28", "receiver": null}, {"caller_nid": "c_users_user_source_repos_axiom_malx_ai_advancedfeaturestate_malx_ai_workspaceadvancedstatepersistence_save", "callee": "CreateDirectory", "is_member_call": true, "source_file": "C:\\Users\\user\\source\\repos\\Axiom\\Malx_AI\\AdvancedFeatureState.cs", "source_location": "L138", "receiver": null}, {"caller_nid": "c_users_user_source_repos_axiom_malx_ai_advancedfeaturestate_malx_ai_workspaceadvancedstatepersistence_save", "callee": "WriteAllText", "is_member_call": true, "source_file": "C:\\Users\\user\\source\\repos\\Axiom\\Malx_AI\\AdvancedFeatureState.cs", "source_location": "L139", "receiver": null}, {"caller_nid": "c_users_user_source_repos_axiom_malx_ai_advancedfeaturestate_malx_ai_workspaceadvancedstatepersistence_save", "callee": "Serialize", "is_member_call": true, "source_file": "C:\\Users\\user\\source\\repos\\Axiom\\Malx_AI\\AdvancedFeatureState.cs", "source_location": "L139", "receiver": null}, {"caller_nid": "c_users_user_source_repos_axiom_malx_ai_advancedfeaturestate_malx_ai_workspaceadvancedstatepersistence_load", "callee": "Load<WorkspaceAdvancedStateSnapshot>", "is_member_call": true, "source_file": "C:\\Users\\user\\source\\repos\\Axiom\\Malx_AI\\AdvancedFeatureState.cs", "source_location": "L144", "receiver": null}, {"caller_nid": "c_users_user_source_repos_axiom_malx_ai_advancedfeaturestate_malx_ai_chatadvancedstatepersistence_save", "callee": "CreateDirectory", "is_member_call": true, "source_file": "C:\\Users\\user\\source\\repos\\Axiom\\Malx_AI\\AdvancedFeatureState.cs", "source_location": "L160", "receiver": null}, {"caller_nid": "c_users_user_source_repos_axiom_malx_ai_advancedfeaturestate_malx_ai_chatadvancedstatepersistence_save", "callee": "WriteAllText", "is_member_call": true, "source_file": "C:\\Users\\user\\source\\repos\\Axiom\\Malx_AI\\AdvancedFeatureState.cs", "source_location": "L161", "receiver": null}, {"caller_nid": "c_users_user_source_repos_axiom_malx_ai_advancedfeaturestate_malx_ai_chatadvancedstatepersistence_save", "callee": "Serialize", "is_member_call": true, "source_file": "C:\\Users\\user\\source\\repos\\Axiom\\Malx_AI\\AdvancedFeatureState.cs", "source_location": "L161", "receiver": null}, {"caller_nid": "c_users_user_source_repos_axiom_malx_ai_advancedfeaturestate_malx_ai_chatadvancedstatepersistence_load", "callee": "Load<ChatAdvancedStateSnapshot>", "is_member_call": true, "source_file": "C:\\Users\\user\\source\\repos\\Axiom\\Malx_AI\\AdvancedFeatureState.cs", "source_location": "L166", "receiver": null}, {"caller_nid": "c_users_user_source_repos_axiom_malx_ai_advancedfeaturestate_malx_ai_chatadvancedstatepersistence_getmostfrequentmodelcombo", "callee": "FirstOrDefault", "is_member_call": true, "source_file": "C:\\Users\\user\\source\\repos\\Axiom\\Malx_AI\\AdvancedFeatureState.cs", "source_location": "L221", "receiver": null}, {"caller_nid": "c_users_user_source_repos_axiom_malx_ai_advancedfeaturestate_malx_ai_chatadvancedstatepersistence_getmostfrequentmodelcombo", "callee": "Select", "is_member_call": true, "source_file": "C:\\Users\\user\\source\\repos\\Axiom\\Malx_AI\\AdvancedFeatureState.cs", "source_location": "L221", "receiver": null}, {"caller_nid": "c_users_user_source_repos_axiom_malx_ai_advancedfeaturestate_malx_ai_chatadvancedstatepersistence_getmostfrequentmodelcombo", "callee": "OrderByDescending", "is_member_call": true, "source_file": "C:\\Users\\user\\source\\repos\\Axiom\\Malx_AI\\AdvancedFeatureState.cs", "source_location": "L221", "receiver": null}, {"caller_nid": "c_users_user_source_repos_axiom_malx_ai_advancedfeaturestate_malx_ai_chatadvancedstatepersistence_getmostfrequentmodelcombo", "callee": "GroupBy", "is_member_call": true, "source_file": "C:\\Users\\user\\source\\repos\\Axiom\\Malx_AI\\AdvancedFeatureState.cs", "source_location": "L221", "receiver": null}, {"caller_nid": "c_users_user_source_repos_axiom_malx_ai_advancedfeaturestate_malx_ai_chatadvancedstatepersistence_getmostfrequentmodelcombo", "callee": "Count", "is_member_call": true, "source_file": "C:\\Users\\user\\source\\repos\\Axiom\\Malx_AI\\AdvancedFeatureState.cs", "source_location": "L223", "receiver": null}]}